simplesubnet/simple_subnet/__init__.py
simplesubnet/simple_subnet/subnet.py
simplesubnet-0.1.5.dist-info/METADATA
simplesubnet-0.1.5.dist-info/WHEEL
simplesubnet-0.1.5.dist-info/RECORD
